dff.v
`timescale 1ns/1ns

module dff (input d,  
              input rst,  
              input clk,  
              output reg q);  
  
    always @ (posedge clk or posedge rst) begin
       if (rst)  
          q <= 1'b0;  
       else  
          q <= d;  
    end
endmodule

fulladder.v
`timescale 1ns/1ns



module fulladder (input X, input Y, input Ci, output S, output Co);  
  
   assign {Co, S} = X + Y + Ci;  
endmodule

CSA.v
`timescale 1ns/1ns

`include "fulladder.v"
`include "dff.v"

module CSA(input clk, input rst, input x, input y, output sum);    
 
    wire fa_cout, fa_sum, dff_carry_out;
    //reg fa_sum;
    fulladder fa(x, y, dff_carry_out, fa_sum, fa_cout);
    
    dff dff_sum(fa_sum, rst, clk, sum);
    dff dff_carry(fa_cout, rst, clk, dff_carry_out);    

endmodule

CSA_tb.v
// file: CSA_tb.v
// author: @omar_elsayed
// Testbench for CSA

`timescale 1ns/1ns

module CSA_tb;

	//Inputs
	reg clk;
	reg rst;
	reg x;
	reg y;
	

	//Outputs
	wire sum;
	


	//Instantiation of Unit Under Test
	CSA uut (
		.clk(clk),
		.rst(rst),
		.x(x),
		.y(y),
        .sum(sum)
	);


	initial begin

    $dumpfile("CSA_tb.vcd");
    $dumpvars(0, CSA_tb);
	//Inputs initialization
        rst = 0;
        rst = 1;

        #20;
        rst = 0;
	    x = 1;
		y= 0;

        #20;
        x = 1;
        y = 1;

        #20;
        x = 0;
        y = 0;

    #1000 $finish;
    end

    initial begin
	//Wait for the reset
        clk = 0;
        forever #10 clk = ~clk;
	end

endmodule

CSA_tb.vcd
$date
	Sat Mar 13 20:57:42 2021
$end
$version
	Icarus Verilog
$end
$timescale
	1ns
$end
$scope module CSA_tb $end
$var wire 1 ! sum $end
$var reg 1 " clk $end
$var reg 1 # rst $end
$var reg 1 $ x $end
$var reg 1 % y $end
$scope module uut $end
$var wire 1 " clk $end
$var wire 1 # rst $end
$var wire 1 $ x $end
$var wire 1 % y $end
$var wire 1 ! sum $end
$var wire 1 & fa_sum $end
$var wire 1 ' fa_cout $end
$var wire 1 ( dff_carry_out $end
$scope module dff_carry $end
$var wire 1 " clk $end
$var wire 1 # rst $end
$var wire 1 ' d $end
$var reg 1 ( q $end
$upscope $end
$scope module dff_sum $end
$var wire 1 " clk $end
$var wire 1 # rst $end
$var wire 1 & d $end
$var reg 1 ! q $end
$upscope $end
$scope module fa $end
$var wire 1 ( Ci $end
$var wire 1 $ X $end
$var wire 1 % Y $end
$var wire 1 & S $end
$var wire 1 ' Co $end
$upscope $end
$upscope $end
$upscope $end
$enddefinitions $end
#0
$dumpvars
0(
x'
x&
x%
x$
1#
0"
0!
$end
#10
1"
#20
1&
0'
0"
0%
1$
0#
#30
1!
1"
#40
0&
1'
0"
1%
#50
1&
1(
0!
1"
#60
0'
0"
0%
0$
#70
0&
1!
0(
1"
#80
0"
#90
0!
1"
