dff.v
`timescale 1ns/1ns

module dff (input d,  
              input rst,  
              input clk,  
              output reg q);  
  
    always @ (posedge clk or posedge rst) begin
       if (rst)  
          q <= 1'b0;  
       else  
          q <= d;  
    end
endmodule

TCMP.v
`timescale 1ns/1ns

//`include "dff.v"
module TCMP(input A, input clk, input rst, output S);
    
    wire ff2_out, or_out, xor_out;

    xor xor1(xor_out, A, ff2_out);

    or or1(or_out, A, ff2_out);

    
    dff dff1(xor_out, rst, clk, S);
    dff dff2(or_out, rst, clk, ff2_out);

endmodule

TCMP_tb.v
// file: CSA_tb.v
// author: @omar_elsayed
// Testbench for CSA

`timescale 1ns/1ns

module TCMP_tb;
	//Inputs
	reg clk;
	reg rst;
	reg A;

	

	//Outputs
	wire S;
	


	//Instantiation of Unit Under Test
	TCMP uut (
		.clk(clk),
		.rst(rst),
		.A(A),
		.S(S)
	);


	initial begin

    $dumpfile("TCMP_tb.vcd");
    $dumpvars(0, TCMP_tb);
	//Inputs initialization
        rst = 0;
        rst = 1;

        #20;
        rst = 0;
	    A = 0;
		

        #20;
        A = 0;

        #20;
        A = 1;

        #20;
        A = 0;


        #20;
        A = 1;



        #20;
        A = 0;


    #1000 $finish;
    end

    initial begin
	//Wait for the reset
        clk = 0;
        forever #10 clk = ~clk;
	end

endmodule

TCMP_tb.vcd
$date
	Sat Mar 13 21:45:20 2021
$end
$version
	Icarus Verilog
$end
$timescale
	1ns
$end
$scope module TCMP_tb $end
$var wire 1 ! S $end
$var reg 1 " A $end
$var reg 1 # clk $end
$var reg 1 $ rst $end
$scope module uut $end
$var wire 1 " A $end
$var wire 1 # clk $end
$var wire 1 % or_out $end
$var wire 1 $ rst $end
$var wire 1 & xor_out $end
$var wire 1 ' ff2_out $end
$var wire 1 ! S $end
$scope module dff1 $end
$var wire 1 # clk $end
$var wire 1 & d $end
$var wire 1 $ rst $end
$var reg 1 ! q $end
$upscope $end
$scope module dff2 $end
$var wire 1 # clk $end
$var wire 1 % d $end
$var wire 1 $ rst $end
$var reg 1 ' q $end
$upscope $end
$upscope $end
$upscope $end
$enddefinitions $end
#0
$dumpvars
0'
x&
x%
1$
0#
x"
0!
$end
#10
1#
#20
0&
0%
0#
0"
0$
#30
1#
#40
0#
#50
1#
#60
1&
1%
0#
1"
#70
0&
1!
1'
1#
#80
1&
0#
0"
#90
1#
#100
0&
0#
1"
#110
0!
1#
#120
1&
0#
0"
#130
1!
1#
